antistar/__init__.py
antistar/core/__init__.py
antistar/tests/__init__.py
antistar/tests/test_1984.py
antistar-0.1.0.dist-info/licenses/LICENSE.txt
antistar-0.1.0.dist-info/METADATA
antistar-0.1.0.dist-info/WHEEL
antistar-0.1.0.dist-info/top_level.txt
antistar-0.1.0.dist-info/RECORD
