Metadata-Version: 2.4
Name: antistar
Version: 0.1.0
Summary: This project provides a function that returns its positional arguments as a tuple.
Author-email: Johannes <johannes.programming@gmail.com>
License: The MIT License (MIT)
Project-URL: Download, https://pypi.org/project/antistar/#files
Project-URL: Index, https://pypi.org/project/antistar/
Project-URL: Source, https://github.com/johannes-programming/antistar/
Project-URL: Website, https://antistar.johannes-programming.online/
Classifier: Development Status :: 3 - Alpha
Classifier: License :: OSI Approved :: MIT License
Classifier: Natural Language :: English
Classifier: Operating System :: OS Independent
Classifier: Programming Language :: Python
Classifier: Programming Language :: Python :: 3
Classifier: Programming Language :: Python :: 3 :: Only
Classifier: Typing :: Typed
Requires-Python: >=3.11
License-File: LICENSE.txt
Dynamic: license-file
